MANIFEST.in
README.md
requirements.txt
setup.py
SIR.egg-info/PKG-INFO
SIR.egg-info/SOURCES.txt
SIR.egg-info/dependency_links.txt
SIR.egg-info/not-zip-safe
SIR.egg-info/requires.txt
SIR.egg-info/top_level.txt
sir/__init__.py
sir/agent.py
sir/analytics/__init__.py
sir/analytics/api.py
sir/analytics/views.py
sir/api/__init__.py
sir/api/views.py
sir/helpers/FSHelper.py
sir/helpers/SQLite3Helper.py
sir/helpers/__init__.py
sir/helpers/api.py
sir/pmacct_data/__init__.py
sir/pmacct_data/api.py
sir/static/highlight.pack.js
sir/static/style.css
sir/static/highlight_styles/agate.css
sir/static/highlight_styles/androidstudio.css
sir/static/highlight_styles/arta.css
sir/static/highlight_styles/ascetic.css
sir/static/highlight_styles/atelier-cave.dark.css
sir/static/highlight_styles/atelier-cave.light.css
sir/static/highlight_styles/atelier-dune.dark.css
sir/static/highlight_styles/atelier-dune.light.css
sir/static/highlight_styles/atelier-estuary.dark.css
sir/static/highlight_styles/atelier-estuary.light.css
sir/static/highlight_styles/atelier-forest.dark.css
sir/static/highlight_styles/atelier-forest.light.css
sir/static/highlight_styles/atelier-heath.dark.css
sir/static/highlight_styles/atelier-heath.light.css
sir/static/highlight_styles/atelier-lakeside.dark.css
sir/static/highlight_styles/atelier-lakeside.light.css
sir/static/highlight_styles/atelier-plateau.dark.css
sir/static/highlight_styles/atelier-plateau.light.css
sir/static/highlight_styles/atelier-savanna.dark.css
sir/static/highlight_styles/atelier-savanna.light.css
sir/static/highlight_styles/atelier-seaside.dark.css
sir/static/highlight_styles/atelier-seaside.light.css
sir/static/highlight_styles/atelier-sulphurpool.dark.css
sir/static/highlight_styles/atelier-sulphurpool.light.css
sir/static/highlight_styles/brown_paper.css
sir/static/highlight_styles/brown_papersq.png
sir/static/highlight_styles/codepen-embed.css
sir/static/highlight_styles/color-brewer.css
sir/static/highlight_styles/dark.css
sir/static/highlight_styles/darkula.css
sir/static/highlight_styles/default.css
sir/static/highlight_styles/docco.css
sir/static/highlight_styles/far.css
