Metadata-Version: 1.0
Name: SIR
Version: 0.10
Summary: SDN Internet Router
Home-page: https://github.com/dbarrosop/sir
Author: David Barroso
Author-email: dbarrosop@dravetech.com
License: Apache License, Version 2.0
Platform: UNKNOWN
